python/delta_sharing/__init__.py
python/delta_sharing/_internal_auth.py
python/delta_sharing/_yarl_patch.py
python/delta_sharing/converter.py
python/delta_sharing/delta_sharing.py
python/delta_sharing/protocol.py
python/delta_sharing/reader.py
python/delta_sharing/rest_client.py
python/delta_sharing/version.py
delta_sharing_custom-1.1.1.dist-info/LICENSE.txt
delta_sharing_custom-1.1.1.dist-info/METADATA
delta_sharing_custom-1.1.1.dist-info/WHEEL
delta_sharing_custom-1.1.1.dist-info/top_level.txt
delta_sharing_custom-1.1.1.dist-info/RECORD
