Metadata-Version: 2.1
Name: delta-sharing-custom
Version: 1.1.1
Summary: Python Connector for Delta Sharing
Home-page: https://github.com/delta-io/delta-sharing/
Author: The Delta Lake Project Authors
Author-email: delta-users@googlegroups.com
License: Apache-2.0
Project-URL: Source, https://github.com/delta-io/delta-sharing
Project-URL: Documentation, https://github.com/delta-io/delta-sharing
Project-URL: Issues, https://github.com/delta-io/delta-sharing/issues
Classifier: Development Status :: 5 - Production/Stable
Classifier: Intended Audience :: Developers
Classifier: License :: OSI Approved :: Apache Software License
Classifier: Operating System :: OS Independent
Classifier: Topic :: Software Development :: Libraries :: Python Modules
Classifier: Programming Language :: Python :: 3.8
Classifier: Programming Language :: Python :: 3.9
Classifier: Programming Language :: Python :: 3.10
Classifier: Programming Language :: Python :: 3.11
Requires-Python: >=3.8
License-File: LICENSE.txt
Requires-Dist: delta-kernel-rust-sharing-wrapper
Requires-Dist: pandas
Requires-Dist: pyarrow>=16.1.0
Requires-Dist: fsspec>=0.7.4
Requires-Dist: requests
Requires-Dist: aiohttp
Requires-Dist: yarl>=1.6.0
Requires-Dist: dataclasses; python_version < "3.8"
Provides-Extra: abfs
Requires-Dist: adlfs; extra == "abfs"
Provides-Extra: adl
Requires-Dist: adlfs; extra == "adl"
Provides-Extra: gcs
Requires-Dist: gcsfs; extra == "gcs"
Provides-Extra: gs
Requires-Dist: gcsfs; extra == "gs"
Provides-Extra: s3
Requires-Dist: s3fs; extra == "s3"
